confessionscommenter/__init__.py
confessionscommenter/api_utils.py
confessionscommenter/commandline_utils.py
confessionscommenter/general_utils.py
confessionscommenter/image_clipboard.py
confessionscommenter/main.py
confessionscommenter/meme_data.json
confessionscommenter/meme_utils.py
confessionscommenter-0.0.11.dist-info/LICENSE
confessionscommenter-0.0.11.dist-info/METADATA
confessionscommenter-0.0.11.dist-info/WHEEL
confessionscommenter-0.0.11.dist-info/top_level.txt
confessionscommenter-0.0.11.dist-info/RECORD
