Metadata-Version: 2.1
Name: confessionscommenter
Version: 0.0.11
Summary: Autogenerate Comments for Facebook Posts
Home-page: https://github.com/AkshajK/confessionscommenter
Author: Raul Alcantara, Erick Gbordzoe, Akshaj Kadaveru, Sean Elliott, Helen Lu
Author-email: shareconfessionscommenter@gmail.com
License: UNKNOWN
Project-URL: Bug Tracker, https://github.com/AkshajK/confessionscommenter/issues
Platform: UNKNOWN
Classifier: Programming Language :: Python :: 3
Classifier: License :: OSI Approved :: MIT License
Classifier: Operating System :: OS Independent
Requires-Python: >=3.6
Requires-Dist: rich
Requires-Dist: facebook-scraper
Requires-Dist: pyperclip
Requires-Dist: transformers
Requires-Dist: tensorflow
Requires-Dist: nltk
Requires-Dist: pillow
Requires-Dist: pywin32 ; platform_system == "Windows"
